djangocms_listyle/__init__.py
djangocms_listyle/cms_plugins.py
djangocms_listyle/models.py
djangocms_listyle/migrations/0001_initial.py
djangocms_listyle/migrations/__init__.py
djangocms_listyle/templates/djangocms_listyle/index.html
djangocms_listyle-0.1.7.dist-info/LICENSE.md
djangocms_listyle-0.1.7.dist-info/METADATA
djangocms_listyle-0.1.7.dist-info/WHEEL
djangocms_listyle-0.1.7.dist-info/top_level.txt
djangocms_listyle-0.1.7.dist-info/RECORD
