Metadata-Version: 2.1
Name: djangocms-listyle
Version: 0.1.7
Summary: Adds a plugin to embed an ordered or unordered list to Django CMS. Children are automatically wrapped in <li> tags.
Home-page: https://github.com/djangocms-listyle
Author: Ben Miller
Author-email: mail@benkmiller.com
License: GNU General Public License v3 (GPLv3), see LICENSE.md
Platform: UNKNOWN
Classifier: Development Status :: 4 - Beta
Classifier: Environment :: Web Environment
Classifier: Framework :: Django
Classifier: Intended Audience :: Developers
Classifier: License :: OSI Approved :: GNU General Public License v3 (GPLv3)
Classifier: Operating System :: OS Independent
Classifier: Programming Language :: Python
Classifier: Topic :: Internet :: WWW/HTTP
Classifier: Topic :: Internet :: WWW/HTTP :: Dynamic Content
Classifier: Topic :: Software Development :: Libraries :: Application Frameworks
Classifier: Topic :: Software Development :: Libraries :: Python Modules
Requires-Dist: django-cms
Requires-Dist: djangocms-style
